tqbus_sdk/__init__.py
tqbus_sdk/tqsystem.py
tqbus_sdk/banca/__init__.py
tqbus_sdk/banca/generics.py
tqbus_sdk/crm/__init__.py
tqbus_sdk/crm/countries.py
tqbus_sdk/crm/generics.py
tqbus_sdk/crm/tqclients.py
tqbus_sdk/gis/__init__.py
tqbus_sdk/gis/endorsements.py
tqbus_sdk/gis/generics.py
tqbus_sdk/gis/policies.py
tqbus_sdk/gis/quotations.py
tqbus_sdk/lms/__init__.py
tqbus_sdk/lms/generics.py
tqbus_sdk-0.1.83.dist-info/METADATA
tqbus_sdk-0.1.83.dist-info/WHEEL
tqbus_sdk-0.1.83.dist-info/RECORD
