Metadata-Version: 2.4
Name: tqbus-sdk
Version: 0.1.83
Author-email: Rigan <it@turnkeyafrica.com>
Requires-Python: <4.0,>=3.8
Requires-Dist: exrex>=0.12.0
Requires-Dist: pydantic>=2.10.6
Requires-Dist: requests>=2.32.3
